gen3datamodel/__init__.py
gen3datamodel/__main__.py
gen3datamodel/gdc_postgres_admin.py
gen3datamodel/models/__init__.py
gen3datamodel/models/indexes.py
gen3datamodel/models/misc.py
gen3datamodel/models/notifications.py
gen3datamodel/models/reports.py
gen3datamodel/models/submission.py
gen3datamodel/models/utils.py
gen3datamodel/models/versioned_nodes.py
gen3datamodel/query.py
gen3datamodel/validators/__init__.py
gen3datamodel/validators/graph_validators.py
gen3datamodel/validators/json_validators.py
gen3datamodel/viz/__init__.py
gen3datamodel/xml_mappings/tcga_clinical.yaml
gen3datamodel-4.0.1.dist-info/METADATA
gen3datamodel-4.0.1.dist-info/WHEEL
gen3datamodel-4.0.1.dist-info/licenses/LICENSE
gen3datamodel-4.0.1.dist-info/RECORD
