Metadata-Version: 2.4
Name: gen3datamodel
Version: 4.0.1
Summary: 
License: Apache-2.0
License-File: LICENSE
Author: CTDS UChicago
Author-email: cdis@uchicago.edu
Requires-Python: >=3.13,<4
Classifier: License :: OSI Approved :: Apache Software License
Classifier: Programming Language :: Python :: 3
Classifier: Programming Language :: Python :: 3.13
Classifier: Programming Language :: Python :: 3.14
Requires-Dist: cdislogging (>=1)
Requires-Dist: dictionaryutils (>=4.0)
Requires-Dist: graphviz
Requires-Dist: jsonschema (<5)
Requires-Dist: psqlgraph (>=3.0.2)
Requires-Dist: pytz
Requires-Dist: rfc3339-validator (<1)
Requires-Dist: sqlalchemy (<3)
Project-URL: Homepage, https://gen3.org/
Project-URL: Repository, https://github.com/uc-cdis/gen3datamodel
